<?xml version="1.0" encoding="utf-8" ?>
<elements>
    <info>
        <name>Lost Vaults: Shields and Bracers</name>
        <description>Lost Vaults: Shields and Bracers</description>
        <author url="https://www.reddit.com/user/MrBakudan/">u/MrBakudan</author>
        <update version="0.0.1">
            <file name="shields-bracers.xml" url="https://raw.githubusercontent.com/community-elements/elements-reddit/master/reddit/reddit-unearthed-arcana/lost-vaults/shields-bracers.xml" />
        </update>
    </info>

</elements>